MANIFEST.in
README.rst
setup.py
urllib3_fixed/__init__.py
urllib3_fixed/_collections.py
urllib3_fixed/connection.py
urllib3_fixed/connectionpool.py
urllib3_fixed/exceptions.py
urllib3_fixed/fields.py
urllib3_fixed/filepost.py
urllib3_fixed/poolmanager.py
urllib3_fixed/request.py
urllib3_fixed/response.py
urllib3_fixed.egg-info/PKG-INFO
urllib3_fixed.egg-info/SOURCES.txt
urllib3_fixed.egg-info/dependency_links.txt
urllib3_fixed.egg-info/top_level.txt
urllib3_fixed/contrib/__init__.py
urllib3_fixed/contrib/appengine.py
urllib3_fixed/contrib/ntlmpool.py
urllib3_fixed/contrib/pyopenssl.py
urllib3_fixed/contrib/securetransport.py
urllib3_fixed/contrib/socks.py
urllib3_fixed/contrib/_securetransport/__init__.py
urllib3_fixed/contrib/_securetransport/bindings.py
urllib3_fixed/contrib/_securetransport/low_level.py
urllib3_fixed/packages/__init__.py
urllib3_fixed/packages/ordered_dict.py
urllib3_fixed/packages/six.py
urllib3_fixed/packages/backports/__init__.py
urllib3_fixed/packages/backports/makefile.py
urllib3_fixed/packages/ssl_match_hostname/__init__.py
urllib3_fixed/packages/ssl_match_hostname/_implementation.py
urllib3_fixed/util/__init__.py
urllib3_fixed/util/connection.py
urllib3_fixed/util/request.py
urllib3_fixed/util/response.py
urllib3_fixed/util/retry.py
urllib3_fixed/util/selectors.py
urllib3_fixed/util/ssl_.py
urllib3_fixed/util/timeout.py
urllib3_fixed/util/url.py
urllib3_fixed/util/wait.py