Metadata-Version: 1.1
Name: urllib3-fixed
Version: 1.0.1
Summary: A city selector for django xadmin
Home-page: https://www.example.com/
Author: wp
Author-email: wpsmoly@gmail.com
License: BSD License
Platform: UNKNOWN
Classifier: Intended Audience :: Developers
Classifier: License :: OSI Approved :: BSD License
Classifier: Operating System :: OS Independent
Classifier: Programming Language :: Python
Classifier: Topic :: Internet :: WWW/HTTP
Classifier: Topic :: Internet :: WWW/HTTP :: Dynamic Content
